<?xml version="1.0" encoding="UTF-8"?>
<root>
	<server>
		<host>localhost</host>
		<port>9091</port>
	</server>
	<deep_learning>
		<protoext>conf/deep_learning/bvlc_googlenet.prototxt</protoext>
		<mode>conf/deep_learning/bvlc_googlenet.caffemodel</mode>
		<labels>conf/deep_learning/synset_words.txt</labels>
	</deep_learning>
	<object_dection>
		<protoext>conf/object_dection/MobileNetSSD_deploy.prototxt.txt</protoext>
		<mode>conf/object_dection/MobileNetSSD_deploy.caffemodel</mode>
		<labels></labels>
	</object_dection>
</root>